celery_testutils/__init__.py
celery_testutils/__version__.py
celery_testutils/config.py
celery_testutils/testcase.py
celery_testutils/tests.py
celery_testutils/worker.py
celery_testutils-0.1.2.dist-info/DESCRIPTION.rst
celery_testutils-0.1.2.dist-info/METADATA
celery_testutils-0.1.2.dist-info/RECORD
celery_testutils-0.1.2.dist-info/WHEEL
celery_testutils-0.1.2.dist-info/metadata.json
celery_testutils-0.1.2.dist-info/top_level.txt
