Metadata-Version: 2.0
Name: celery-testutils
Version: 0.1.2
Summary: Run a monitored Celery worker for integration tests that depend on Celery tasks
Home-page: http://github.com/kevinseelbach/celery_testutils
Author: Kevin Seelbach
Author-email: kevin.seelbach@gmail.com
License: BSD license, see LICENSE
Keywords: celery,testing,integration,test
Platform: UNKNOWN
Requires-Dist: celery (>=3.0.19)
